LICENSE
README.md
pychaterr/__init__.py
pychaterr/chaterr.py
pychaterr-0.1.0.dist-info/METADATA
pychaterr-0.1.0.dist-info/WHEEL
pychaterr-0.1.0.dist-info/licenses/LICENSE
pychaterr-0.1.0.dist-info/RECORD
