Metadata-Version: 2.1
Name: PyChatErr
Version: 0.1.0
Summary: Python generic error handler powered by ChatGPT
Project-URL: Homepage, https://github.com/omab/pychaterr
Project-URL: Bug Tracker, https://github.com/omab/pychaterr/issues
Author-email: Matías Aguirre <matiasaguirre@gmail.com>
License-File: LICENSE
Classifier: License :: OSI Approved :: BSD License
Classifier: Operating System :: OS Independent
Classifier: Programming Language :: Python :: 3
Requires-Python: >=3.7
Requires-Dist: openai
